{
  "userId": "3333333333",
  "profile": {
    "name": "Kavya Iyer",
    "location": "Chennai, Tamil Nadu",
    "profession": "UX Designer",
    "age": 26,
    "monthlyIncome": 90000,
    "riskProfile": "moderate_aggressive",
    "financialLiteracy": "high",
    "assetAllocation": {
      "equity": 65,
      "debt": 20,
      "gold": 5,
      "cash": 10
    },
    "debtProfile": {
      "creditCard": 30000,
      "personalLoan": 0,
      "homeLoan": 0
    },
    "spendingPattern": "tech_savvy",
    "investmentFocus": "direct_equity",
    "avatar": 3,
    "panCard": "ABCDE3333X",
    "aadharCard": "3333-3333-33"
  },
  "bankAccounts": [
    {
      "accountId": "PRIMARY_001",
      "bankName": "HDFC Bank",
      "accountType": "Salary",
      "balance": 101171
    },
    {
      "accountId": "SECONDARY_001",
      "bankName": "SBI",
      "accountType": "Savings",
      "balance": 43359
    }
  ],
  "totalBankBalance": 144530,
  "mutualFunds": [
    {
      "schemeName": "Axis Small Cap Fund - Direct Growth",
      "sipAmount": 29250,
      "currentValue": 290228,
      "investedAmount": 263250,
      "returns": 26978,
      "returnsPercentage": 10.25
    },
    {
      "schemeName": "Parag Parikh Flexi Cap Fund - Direct Growth",
      "sipAmount": 29250,
      "currentValue": 380598,
      "investedAmount": 321750,
      "returns": 58848,
      "returnsPercentage": 18.29
    }
  ],
  "totalMutualFunds": 670826,
  "stocks": [
    {
      "symbol": "INFY",
      "companyName": "Infosys Limited",
      "currentValue": 351000,
      "investedAmount": 315900,
      "returns": 35100,
      "quantity": 45
    }
  ],
  "totalStocks": 351000,
  "goldInvestments": [
    {
      "type": "Digital Gold",
      "platform": "Paytm Gold",
      "currentValue": 13500,
      "grams": 2.48
    }
  ],
  "totalGold": 13500,
  "creditCards": [
    {
      "bankName": "HDFC Bank",
      "cardType": "Credit Card",
      "creditLimit": 120000,
      "outstandingAmount": 30000,
      "minimumDue": 1500
    }
  ],
  "monthlySpending": {
    "housing": 27000,
    "food": 13500,
    "transport": 9000,
    "investments": 10800,
    "entertainment": 7200,
    "miscellaneous": 9000
  },
  "netWorth": {
    "totalAssets": 1179856,
    "totalLiabilities": 30000,
    "netWorth": 1149856,
    "breakdown": {
      "bankAccounts": 144530,
      "mutualFunds": 670826,
      "stocks": 351000,
      "gold": 13500,
      "creditCardDebt": -30000,
      "loans": 0,
      "nps": 0
    }
  },
  "recentTransactions": [],
  "goals": [],
  "metadata": {
    "createdAt": "2025-07-22T04:36:35.022Z",
    "updatedAt": "2025-07-22T04:36:35.022Z",
    "version": "1.0",
    "dataSource": "expert_generated"
  }
}